discordial/__init__.py
discordial/gateway/__init__.py
discordial/gateway/client.py
discordial/gateway/dispatcher.py
discordial/gateway/intents.py
discordial/gateway/resolver.py
discordial/gateway/static.py
discordial-1.0.5.dist-info/LICENSE
discordial-1.0.5.dist-info/METADATA
discordial-1.0.5.dist-info/WHEEL
discordial-1.0.5.dist-info/top_level.txt
discordial-1.0.5.dist-info/RECORD
