Metadata-Version: 2.1
Name: discordial
Version: 1.0.5
Summary: A lightweight library for Discord
Home-page: https://github.com/vcokltfre/discordial
Author: vcokltfre
Author-email: vcokltfre@gmail.com
License: UNKNOWN
Platform: UNKNOWN
Classifier: Programming Language :: Python :: 3
Classifier: License :: OSI Approved :: MIT License
Classifier: Operating System :: OS Independent
Requires-Python: >=3.6
Requires-Dist: websockets
Requires-Dist: requests
Requires-Dist: holster
